tree_sitter_embedded-template/queries/highlights.scm
tree_sitter_embedded-template/queries/injections-erb.scm
tree_sitter_embedded-template/queries/injections-ejs.scm
tree_sitter_embedded_template-0.23.2.dist-info/RECORD
tree_sitter_embedded_template-0.23.2.dist-info/LICENSE
tree_sitter_embedded_template-0.23.2.dist-info/WHEEL
tree_sitter_embedded_template-0.23.2.dist-info/top_level.txt
tree_sitter_embedded_template-0.23.2.dist-info/METADATA
tree_sitter_embedded_template/__init__.pyi
tree_sitter_embedded_template/binding.c
tree_sitter_embedded_template/__init__.py
tree_sitter_embedded_template/py.typed
tree_sitter_embedded_template/_binding.abi3.so
